halonet_pytorch/__init__.py
halonet_pytorch/halonet_pytorch.py
halonet_pytorch-0.0.4.dist-info/LICENSE
halonet_pytorch-0.0.4.dist-info/METADATA
halonet_pytorch-0.0.4.dist-info/WHEEL
halonet_pytorch-0.0.4.dist-info/top_level.txt
halonet_pytorch-0.0.4.dist-info/RECORD
